<!DOCTYPE struts PUBLIC
"-//Apache Software Foundation//DTD Struts Configuration 2.0//EN"
"http://struts.apache.org/dtds/struts-2.0.dtd">

<struts>
    <package name="default" namespace="/" extends="struts-default">
        
        <action name="Login" class="com.exavalu.models.User" method="doLogin">
            <result name="SUCCESS">employeeDetails.jsp</result>
            <result name="FAILURE">login.jsp</result>
        </action>  
        
        <action name="SignUp" class="com.exavalu.models.User" method="doSignUp">
            <result name="SUCCESS">login.jsp</result>
            <result name="FAILURE">signup.jsp</result>
        </action>  
        
        <action name="employeeDetails" class="com.exavalu.models.Employee" method="getAllEmployees">
            <result name="SUCCESS">employeeDetails.jsp</result>
            <result name="FAILURE">error.jsp</result>
        </action>  
        
        <action name="AddEmp" class="com.exavalu.models.Employee" method="insertEmployee">
            <result name="SUCCESS">employeeDetails.jsp</result>
            <result name="FAILURE">addemp.jsp</result>
        </action>
          
        <action name="Search" class="com.exavalu.models.Employee" method="search">
            <result name="SUCCESS">searchEmployee.jsp</result>
            <result name="FAILURE">employeeDetails.jsp</result>
        </action>
        
        <action name="EditEmployee" class="com.exavalu.models.Employee" method="editEmployee">
            <result name="SUCCESS">editemployee.jsp</result>
            <result name="FAILURE">error.jsp</result>
        </action>
        <action name="SignUp" class="com.exavalu.models.User" method="doSignUp">
            <result name="SUCCESS">login.jsp</result>
            <result name="FAILURE">signup.jsp</result>
        </action> 
        <action name="SaveEmployee" class="com.exavalu.models.Employee" method="updateService">
            <result name="SUCCESS">employeeDetails.jsp</result>
            <result name="FAILURE">editemployee.jsp</result>
        </action> 
        
        <action name="Logout" class="com.exavalu.models.Employee" method="doLogout">
            <result name="SUCCESS">logout.jsp</result>
            <result name="FAILURE">employeeDetails.jsp</result>
        </action> 
        
        
        <action name="PreSignUp" class="com.exavalu.models.User" method="doPreSignUp">
            <result name="SUCCESS">signup.jsp</result>
            <result name="FAILURE">login.jsp</result>
            <result name="STATELIST">statelist.jsp</result>
            <result name="DISTLIST">districtlist.jsp</result>
        </action> 
     
     
             
    </package>
</struts>
